xmcd_projection/__init__.py
xmcd_projection/color.py
xmcd_projection/data_loading.py
xmcd_projection/image.py
xmcd_projection/mesh.py
xmcd_projection/mesh_visualisation.py
xmcd_projection/projection.py
xmcd_projection/raytracing.py
xmcd_projection/stl_visualisation.py
xmcd_projection/version.py
XMCD_Projection-1.0.1.dist-info/LICENSE
XMCD_Projection-1.0.1.dist-info/METADATA
XMCD_Projection-1.0.1.dist-info/WHEEL
XMCD_Projection-1.0.1.dist-info/top_level.txt
XMCD_Projection-1.0.1.dist-info/RECORD
