Metadata-Version: 2.1
Name: XMCD-Projection
Version: 1.0.1
Summary: Library for simulating XMCD projection signal
Home-page: UNKNOWN
Author: Luka Skoric
License: MIT LICENSE
Platform: UNKNOWN
Requires-Dist: trimesh (>=3.9.12)
Requires-Dist: numpy (==1.20.2)
Requires-Dist: matplotlib (>=3.4.1)
Requires-Dist: numba (>=0.53.1)
Requires-Dist: joblib (>=1.0.1)
Requires-Dist: PyQt5 (>=5.15.4)
Requires-Dist: pyqtgraph (>=0.11.1)
Requires-Dist: scikit-image (>=0.18.1)
Requires-Dist: scipy (>=1.6.2)
Requires-Dist: PyOpenGL (>=3.1.5)
Requires-Dist: cached-property (>=1.5.2)
Requires-Dist: pandas (>=1.0.5)
Requires-Dist: meshio (>=4.0.16)
Requires-Dist: tqdm (<=4.46.1)
